Workbook

Sheet Start Here
A1: ACCOUNTING PROJECT PORTFOLIO
A3: Portfolio case study: NigerTech Retail Ltd. (fictional Nigerian SME)
A5: Purpose | B5: Demonstrate practical bookkeeping, bank reconciliation, financial reporting, budgeting, inventory control, and management analysis.
A6: Period | B6: Illustrative month: September 2026. All data are fictional and created for training/portfolio use.
A7: Currency | B7: Nigerian naira (₦). Amounts are illustrative, not tax or investment advice.
A8: Workbook workflow | B8: Review the raw registers first, then reconcile the bank, review the trial balance and statements, and finish with the management dashboard.
A9: Quality control | B9: Check formula outputs, investigate reconciling items, and document assumptions before presenting any report to a client.
A10: GitHub safety | B10: Upload only fictional/anonymized data. Do not upload client names, account numbers, passwords, tax IDs, or confidential records.
A11: Portfolio use | B11: Pair this workbook with the PDF case report and README.md. Add screenshots of dashboards if useful, but avoid sensitive information.
A14: Suggested repository name | B14: nigertech-retail-accounting-portfolio
A16: Sheets included
A17: Sales Register | B17: Daily sales records.
A18: Expense Register | B18: Operating expense transactions.
A19: Cashbook | B19: Cash and bank receipts/payments ledger.
A20: Bank Reconciliation | B20: Illustrative bank statement matching and outstanding items.
A21: Inventory | B21: Stock movement and closing inventory calculation.
A22: Trial Balance | B22: Summary of selected ledger balances.
A23: Income Statement | B23: Revenue, cost of sales, expenses, and profit.
A24: Balance Sheet | B24: Illustrative assets, liabilities, and equity.
A25: Budget vs Actual | B25: Management comparison and variance analysis.
A26: Dashboard | B26: KPI summary and sales chart.

Sheet Dashboard
A1: MANAGEMENT DASHBOARD
A2: NigerTech Retail Ltd. | September 2026 | Fictional portfolio data
A3: KPI | B3: Value | C3: Interpretation
A4: Sales revenue | B4: ='Sales Register'!G17 | C4: Total recorded sales for the period.
A5: Operating expenses | B5: ='Expense Register'!F15 | C5: Total listed operating expenses.
A6: Cost of sales | B6: ='Income Statement'!B5 | C6: Calculated from units sold and unit cost.
A7: Gross profit | B7: ='Income Statement'!B6 | C7: Revenue less cost of sales.
A8: Net profit before tax | B8: ='Income Statement'!B8 | C8: Gross profit less listed operating expenses.
A9: Closing inventory | B9: =Inventory!H10 | C9: Closing stock value based on the stock register.
A28: Dashboard caveat | B28: These indicators are illustrative and depend on the sample data and formula assumptions. Validate source data and accounting classifications before client delivery.

Sheet Sales Register
A1: SALES REGISTER
A2: NigerTech Retail Ltd. | September 2026 | Fictional training data
A3: Date | B3: Invoice No. | C3: Customer | D3: Product | E3: Qty | F3: Unit Price (₦) | G3: Sales (₦) | H3: Payment Method
A4: 46266 | B4: INV-001 | C4: Walk-in Customer | D4: Laptop accessories | E4: 4 | F4: 18000 | G4: =E4*F4 | H4: Transfer
A5: 46267 | B5: INV-002 | C5: Brightway School | D5: Printer paper carton | E5: 10 | F5: 12500 | G5: =E5*F5 | H5: Bank
A6: 46268 | B6: INV-003 | C6: Walk-in Customer | D6: USB flash drive | E6: 15 | F6: 4500 | G6: =E6*F6 | H6: Cash
A7: 46270 | B7: INV-004 | C7: Oakline Ventures | D7: Wireless mouse | E7: 12 | F7: 6500 | G7: =E7*F7 | H7: Transfer
A8: 46272 | B8: INV-005 | C8: Walk-in Customer | D8: Keyboard | E8: 8 | F8: 8500 | G8: =E8*F8 | H8: Cash
A9: 46274 | B9: INV-006 | C9: Delta Tutors | D9: Printer paper carton | E9: 14 | F9: 12500 | G9: =E9*F9 | H9: Bank
A10: 46277 | B10: INV-007 | C10: Walk-in Customer | D10: Laptop accessories | E10: 6 | F10: 18000 | G10: =E10*F10 | H10: Transfer
A11: 46280 | B11: INV-008 | C11: Oakline Ventures | D11: USB flash drive | E11: 20 | F11: 4500 | G11: =E11*F11 | H11: Bank
A12: 46283 | B12: INV-009 | C12: Walk-in Customer | D12: Wireless mouse | E12: 10 | F12: 6500 | G12: =E12*F12 | H12: Cash
A13: 46287 | B13: INV-010 | C13: Brightway School | D13: Keyboard | E13: 10 | F13: 8500 | G13: =E13*F13 | H13: Transfer
A14: 46291 | B14: INV-011 | C14: Walk-in Customer | D14: Printer paper carton | E14: 8 | F14: 12500 | G14: =E14*F14 | H14: Cash
A15: 46294 | B15: INV-012 | C15: Delta Tutors | D15: Laptop accessories | E15: 5 | F15: 18000 | G15: =E15*F15 | H15: Bank
F17: TOTAL | G17: =SUM(G4:G15)

Sheet Expense Register
A1: EXPENSE REGISTER
A2: Operating expenses | September 2026 | Fictional training data
A3: Date | B3: Voucher No. | C3: Expense Category | D3: Description | E3: Payment Method | F3: Amount (₦)
A4: 46267 | B4: PV-001 | C4: Rent | D4: Monthly shop rent allocation | E4: Bank | F4: 120000
A5: 46269 | B5: PV-002 | C5: Transport | D5: Delivery and logistics | E5: Cash | F5: 18500
A6: 46271 | B6: PV-003 | C6: Internet | D6: Internet subscription | E6: Transfer | F6: 15000
A7: 46273 | B7: PV-004 | C7: Utilities | D7: Electricity and utilities | E7: Cash | F7: 22000
A8: 46276 | B8: PV-005 | C8: Salaries | D8: Staff wages | E8: Bank | F8: 160000
A9: 46279 | B9: PV-006 | C9: Marketing | D9: Social media promotion | E9: Transfer | F9: 25000
A10: 46282 | B10: PV-007 | C10: Repairs | D10: Minor shop repairs | E10: Cash | F10: 12000
A11: 46285 | B11: PV-008 | C11: Transport | D11: Supplier collection | E11: Cash | F11: 14500
A12: 46288 | B12: PV-009 | C12: Bank Charges | D12: Bank fees | E12: Bank | F12: 3500
A13: 46292 | B13: PV-010 | C13: Office Supplies | D13: Receipt books and stationery | E13: Cash | F13: 9500
E15: TOTAL | F15: =SUM(F4:F13)

Sheet Cashbook
A1: CASHBOOK
A2: Illustrative cash/bank transactions | September 2026
A3: Date | B3: Reference | C3: Narration | D3: Account | E3: Receipts (₦) | F3: Payments (₦) | G3: Running Balance (₦)
A4: 46266 | B4: OB-001 | C4: Opening bank balance | D4: Bank | E4: 500000 | F4: 0 | G4: =E4-F4
A5: 46266 | B5: INV-001 | C5: Sales receipt | D5: Bank | E5: 72000 | F5: 0 | G5: =G4+E5-F5
A6: 46267 | B6: PV-001 | C6: Rent | D6: Bank | E6: 0 | F6: 120000 | G6: =G5+E6-F6
A7: 46267 | B7: INV-002 | C7: Sales receipt | D7: Bank | E7: 125000 | F7: 0 | G7: =G6+E7-F7
A8: 46268 | B8: INV-003 | C8: Cash sales | D8: Cash | E8: 67500 | F8: 0 | G8: =G7+E8-F8
A9: 46269 | B9: PV-002 | C9: Transport | D9: Cash | E9: 0 | F9: 18500 | G9: =G8+E9-F9
A10: 46271 | B10: PV-003 | C10: Internet | D10: Bank | E10: 0 | F10: 15000 | G10: =G9+E10-F10
A11: 46272 | B11: INV-005 | C11: Cash sales | D11: Cash | E11: 68000 | F11: 0 | G11: =G10+E11-F11
A12: 46273 | B12: PV-004 | C12: Utilities | D12: Cash | E12: 0 | F12: 22000 | G12: =G11+E12-F12
A13: 46274 | B13: INV-006 | C13: Sales receipt | D13: Bank | E13: 175000 | F13: 0 | G13: =G12+E13-F13
A14: 46276 | B14: PV-005 | C14: Staff wages | D14: Bank | E14: 0 | F14: 160000 | G14: =G13+E14-F14
A15: 46277 | B15: INV-007 | C15: Sales receipt | D15: Bank | E15: 108000 | F15: 0 | G15: =G14+E15-F15
A16: 46279 | B16: PV-006 | C16: Marketing | D16: Bank | E16: 0 | F16: 25000 | G16: =G15+E16-F16
... A25: 46294 | B25: INV-012 | C25: Sales receipt | D25: Bank | E25: 90000 | F25: 0 | G25: =G24+E25-F25

Sheet Bank Reconciliation
A1: BANK RECONCILIATION
A2: Illustrative reconciliation | Reconcile book balance to bank statement
A3: Item | B3: Amount (₦) | C3: Treatment / Notes
A4: Cashbook bank balance per ledger | B4: =SUM(Cashbook!E4:E25)-SUM(Cashbook!F4:F25) | C4: Based on bank-tagged transactions; see assumption below.
A5: Add: Deposit in transit | B5: 45000 | C5: Recorded in cashbook, not yet reflected by bank.
A6: Less: Unpresented payment | B6: -30000 | C6: Payment issued and recorded, not yet cleared.
A7: Adjusted bank balance | B7: =B5+B6+B7 | C7: Should agree with adjusted bank statement balance.
A8: Bank statement balance (illustrative) | B8: 0 | C8: Enter the actual statement balance for a real engagement.
A9: Difference to investigate | B9: =B8-B9 | C9: A non-zero difference requires investigation.
A11: Control note | B11: This is a training template, not a completed real bank reconciliation. Confirm which cashbook transactions are bank transactions and enter the real bank statement closing balance.

Sheet Inventory
A1: INVENTORY REGISTER
A2: Illustrative perpetual stock card with closing inventory
A3: SKU | B3: Product | C3: Opening Qty | D3: Purchases Qty | E3: Units Sold | F3: Closing Qty | G3: Unit Cost (₦) | H3: Closing Value (₦)
A4: SKU-001 | B4: Laptop accessories | C4: 20 | D4: 10 | E4: 15 | F4: =C4+D4-E4 | G4: 11000 | H4: =F4*G4
A5: SKU-002 | B5: Printer paper carton | C5: 35 | D5: 15 | E5: 32 | F5: =C5+D5-E5 | G5: 8000 | H5: =F5*G5
A6: SKU-003 | B6: USB flash drive | C6: 50 | D6: 20 | E6: 35 | F6: =C6+D6-E6 | G6: 2500 | H6: =F6*G6
A7: SKU-004 | B7: Wireless mouse | C7: 25 | D7: 15 | E7: 22 | F7: =C7+D7-E7 | G7: 3500 | H7: =F7*G7
A8: SKU-005 | B8: Keyboard | C8: 20 | D8: 10 | E8: 18 | F8: =C8+D8-E8 | G8: 5000 | H8: =F8*G8
G10: TOTAL | H10: =SUM(H4:H8)

Sheet Trial Balance
A1: TRIAL BALANCE
A2: Illustrative selected balances | Review account mapping and completeness
A3: Account Code | B3: Account Name | C3: Debit (₦) | D3: Credit (₦)
A4: 1000 | B4: Cash and bank | C4: 0 | D4: 0
A5: 1100 | B5: Accounts receivable | C5: 0 | D5: 0
A6: 1200 | B6: Inventory | C6: 0 | D6: 0
A7: 2000 | B7: Accounts payable | C7: 0 | D7: 0
A8: 3000 | B8: Owner's capital | C8: 0 | D8: 500000
A9: 4000 | B9: Sales revenue | C9: 0 | D9: 1123500
A10: 5000 | B10: Cost of sales | C10: 0 | D10: 0
A11: 6000 | B11: Operating expenses | C11: 0 | D11: 400000
A13: TOTAL | C13: =SUM(C4:C11) | D13: =SUM(D4:D11)
A14: Difference | C14: =C13-D13
A16: Training note | B16: This is a partial, illustrative trial balance scaffold. A production trial balance must include all ledger balances and be balanced before statements are finalized.

Sheet Income Statement
A1: STATEMENT OF PROFIT OR LOSS
A2: NigerTech Retail Ltd. | Illustrative September 2026
A3: Line Item | B3: Amount (₦)
A4: Revenue | B4: ='Sales Register'!G17
A5: Cost of sales | B5: =SUMPRODUCT(Inventory!E4:E8,Inventory!G4:G8)
A6: Gross profit | B6: =B4-B5
A7: Operating expenses | B7: ='Expense Register'!F15
A8: Net profit before tax | B8: =B6-B7
A10: Reporting note | B10: Cost of sales uses units sold × unit cost from the inventory register. For real reporting, reconcile inventory, purchases, returns, VAT/tax treatment, accruals, and other adjustments.

Sheet Balance Sheet
A1: STATEMENT OF FINANCIAL POSITION
A2: Illustrative layout for portfolio practice; complete balances before use
A3: Section | B3: Account | C3: Amount (₦)
A4: Assets | B4: Cash and bank | C4: 0
A5: Assets | B5: Accounts receivable | C5: 0
A6: Assets | B6: Closing inventory | C6: =Inventory!H10
A7: Assets | B7: Total assets | C7: =SUM(C4:C6)
A8: Liabilities | B8: Accounts payable | C8: 0
A9: Liabilities | B9: Total liabilities | C9: =C8
A10: Equity | B10: Owner's capital | C10: 500000
A11: Equity | B11: Current period profit | C11: ='Income Statement'!B8
A12: Equity | B12: Total equity | C12: =SUM(C10:C11)
A13: Check | B13: Liabilities + equity | C13: =C9+C12
A14: Check | B14: Difference (assets less liabilities/equity) | C14: =C7-C13
A16: Important | B16: This statement is an illustrative scaffold and may not balance because several ledger balances are intentionally left at zero. Do not represent it as finalized financial statements.

Sheet Budget vs Actual
A1: BUDGET VS ACTUAL
A2: Management reporting | September 2026 illustrative assumptions
A3: Category | B3: Budget (₦) | C3: Actual (₦) | D3: Variance (₦) | E3: Variance % | F3: Comment
A4: Sales revenue | B4: 1000000 | C4: ='Sales Register'!G17 | D4: =C4-B4 | E4: =IFERROR(D4/B4,0) | F4: Positive variance means actual exceeds budget.
A5: Cost of sales | B5: 400000 | C5: ='Income Statement'!B5 | D5: =C5-B5 | E5: =IFERROR(D5/B5,0) | F5: Review supplier pricing and product mix.
A6: Operating expenses | B6: 420000 | C6: ='Expense Register'!F15 | D6: =C6-B6 | E6: =IFERROR(D6/B6,0) | F6: Investigate material overspend/underspend.
